[
    {
        "userId" : "scott.tiger@example.com",
        "email" : "scott.tiger@example.com",
        "languageId" : "de",
        "countryId" : "DE",
        "timeZoneId" : "CET",
        "salutation" : "Mr",
        "firstName" : "Scott",
        "lastName" : "Tiger",
        "birthday" : "1980-02-10",
        "phoneNo" : "+49123456789",
        "department" : "Tiger Store",
        "floor" : "1st",
        "room" : "88",
        "createdBy" : "the doctor"
    },
    {
        "userId" : "john.doe@ncc.com",
        "email" : "john.doe@ncc.com",
        "languageId" : "de",
        "countryId" : "DE",
        "timeZoneId" : "CET",
        "salutation" : "Mr",
        "firstName" : "John",
        "lastName" : "Doe",
        "birthday" : "1983-02-03",
        "phoneNo" : "+49123456789",
        "department" : "Doe Management",
        "floor" : "3rd",
        "room" : "42",
        "createdBy" : "the doctor"
    }
]
